behavioural_contracts/__init__.py
behavioural_contracts/contract.py
behavioural_contracts/exceptions.py
behavioural_contracts/generator.py
behavioural_contracts/health_monitor.py
behavioural_contracts/models.py
behavioural_contracts/temperature.py
behavioural_contracts/validator.py
behavioural_contracts-0.1.2.dist-info/METADATA
behavioural_contracts-0.1.2.dist-info/WHEEL
behavioural_contracts-0.1.2.dist-info/licenses/LICENSE
behavioural_contracts-0.1.2.dist-info/RECORD
