Metadata-Version: 2.4
Name: behavioural_contracts
Version: 0.1.2
Summary: A Python package for enforcing behavioural contracts in AI agents
Project-URL: Homepage, https://github.com/yourusername/behavioural_contracts
Project-URL: Documentation, https://github.com/yourusername/behavioural_contracts#readme
Project-URL: Repository, https://github.com/yourusername/behavioural_contracts.git
Project-URL: Issues, https://github.com/yourusername/behavioural_contracts/issues
Author-email: Andrew Whitehouse <andrewswhitehouse@gmail.com>
License-Expression: MIT
License-File: LICENSE
Classifier: Development Status :: 4 - Beta
Classifier: Intended Audience :: Developers
Classifier: License :: OSI Approved :: MIT License
Classifier: Programming Language :: Python :: 3
Classifier: Programming Language :: Python :: 3.8
Classifier: Programming Language :: Python :: 3.9
Classifier: Programming Language :: Python :: 3.10
Classifier: Programming Language :: Python :: 3.11
Classifier: Programming Language :: Python :: 3.12
Classifier: Topic :: Software Development :: Libraries :: Python Modules
Classifier: Topic :: Software Development :: Quality Assurance
Requires-Python: >=3.8
Requires-Dist: pydantic>=2.0.0
Requires-Dist: typing-extensions>=4.0.0
Provides-Extra: dev
Requires-Dist: black>=23.0.0; extra == 'dev'
Requires-Dist: build>=1.0.0; extra == 'dev'
Requires-Dist: flake8>=6.1.0; extra == 'dev'
Requires-Dist: isort>=5.0.0; extra == 'dev'
Requires-Dist: mypy>=1.0.0; extra == 'dev'
Requires-Dist: pre-commit>=3.0.0; extra == 'dev'
Requires-Dist: pytest-cov>=4.0.0; extra == 'dev'
Requires-Dist: pytest>=7.0.0; extra == 'dev'
Requires-Dist: ruff>=0.1.0; extra == 'dev'
Requires-Dist: tomli>=2.0.0; extra == 'dev'
Requires-Dist: twine>=4.0.0; extra == 'dev'
